[
  {
    "_id": "5db88a185b66759cfc56bcdd",
    "category": "object name",
    "fact": "Alpha Centauri A",
    "synonyms": [
      "Rigil Kentaurus"
    ]
  },
  {
    "_id": "5db88a185b66759cfc56bce0",
    "category": "object name",
    "fact": "Alpha Centauri B",
    "synonyms": [
      "Proxima Centauri"
    ]
  },
  {
    "_id": "5db88a185b66759cfc56bce2",
    "category": "object name",
    "fact": "Proxima Centauri b",
    "synonyms": [
      "Proxima b"
    ]
  },
  {
    "_id": "5db88a185b66759cfc56bce5",
    "category": "object name",
    "fact": "earth",
    "synonyms": [
      "blue planet",
      "gaia"
    ]
  },
  {
    "_id": "5db88a185b66759cfc56bce5",
    "category": "orbits",
    "fact": "Sun",
    "synonyms": [
      "Sol"
    ]
  }
]